Macropodus-0.0.7.dist-info/DESCRIPTION.rst
Macropodus-0.0.7.dist-info/METADATA
Macropodus-0.0.7.dist-info/RECORD
Macropodus-0.0.7.dist-info/WHEEL
Macropodus-0.0.7.dist-info/metadata.json
Macropodus-0.0.7.dist-info/top_level.txt
macropodus/__init__.py
macropodus/__init_tf_keras.py
macropodus/version.py
macropodus/base/__init__.py
macropodus/base/seg_basic.py
macropodus/base/word2vec.py
macropodus/conf/__init__.py
macropodus/conf/path_config.py
macropodus/conf/path_log.py
macropodus/data/__init__.py
macropodus/data/cache/__init__.py
macropodus/data/dict/macropodus.dict
macropodus/data/dict/pinyin.dict
macropodus/data/dict/user.dict
macropodus/data/embedding/term_char.txt
macropodus/data/embedding/word2vec/w2v_model_wiki_char.vec
macropodus/data/model/__init__.py
macropodus/data/model/ner_albert_people_1998/__init__.py
macropodus/data/model/tag_albert_people_1998/__init__.py
macropodus/data/words_common/__init__.py
macropodus/data/words_common/stop_words.py
macropodus/logs/__init__.py
macropodus/network/__init__.py
macropodus/network/base/__init__.py
macropodus/network/base/embedding.py
macropodus/network/base/graph.py
macropodus/network/graph/__init__.py
macropodus/network/graph/bilstm.py
macropodus/network/graph/bilstm_crf.py
macropodus/network/graph/crf.py
macropodus/network/layers/__init__.py
macropodus/network/layers/albert.py
macropodus/network/layers/crf.py
macropodus/network/layers/keras_lookahead.py
macropodus/network/layers/keras_radam.py
macropodus/network/layers/non_mask_layer.py
macropodus/network/preprocess/__init__.py
macropodus/network/preprocess/preprocess_generator.py
macropodus/network/service/__init__.py
macropodus/network/service/keras_dump.py
macropodus/network/service/server_base.py
macropodus/network/service/server_prdeict.py
macropodus/network/service/server_streamer.py
macropodus/network/service/server_streamer_flask.py
macropodus/network/service/thread_manage.py
macropodus/network/train/__init__.py
macropodus/network/train/train_bilstm.py
macropodus/network/train/train_bilstm_crf.py
macropodus/network/train/train_crf.py
macropodus/preprocess/__init__.py
macropodus/preprocess/tools_clear.py
